openbb_cli/__init__.py
openbb_cli/argparse_translator/__init__.py
openbb_cli/argparse_translator/argparse_argument.py
openbb_cli/argparse_translator/argparse_class_processor.py
openbb_cli/argparse_translator/argparse_translator.py
openbb_cli/argparse_translator/obbject_registry.py
openbb_cli/argparse_translator/reference_processor.py
openbb_cli/argparse_translator/utils.py
openbb_cli/assets/routines/routine_example.openbb
openbb_cli/assets/styles/default/Consolas.ttf
openbb_cli/assets/styles/default/dark.mpfstyle.json
openbb_cli/assets/styles/default/dark.mplrc.json
openbb_cli/assets/styles/default/dark.mplstyle
openbb_cli/assets/styles/default/dark.pltstyle.json
openbb_cli/assets/styles/default/dark.richstyle.json
openbb_cli/assets/styles/default/light.mpfstyle.json
openbb_cli/assets/styles/default/light.mplrc.json
openbb_cli/assets/styles/default/light.mplstyle
openbb_cli/assets/styles/default/light.pltstyle.json
openbb_cli/assets/styles/default/light.richstyle.json
openbb_cli/assets/styles/default/tables.pltstyle.json
openbb_cli/assets/styles/user/openbb.richstyle.json
openbb_cli/cli.py
openbb_cli/config/__init__.py
openbb_cli/config/completer.py
openbb_cli/config/console.py
openbb_cli/config/constants.py
openbb_cli/config/menu_text.py
openbb_cli/config/setup.py
openbb_cli/config/style.py
openbb_cli/controllers/base_controller.py
openbb_cli/controllers/base_platform_controller.py
openbb_cli/controllers/choices.py
openbb_cli/controllers/cli_controller.py
openbb_cli/controllers/hub_service.py
openbb_cli/controllers/platform_controller_factory.py
openbb_cli/controllers/script_parser.py
openbb_cli/controllers/settings_controller.py
openbb_cli/controllers/utils.py
openbb_cli/models/settings.py
openbb_cli/session.py
openbb_cli/utils/utils.py
openbb_cli-1.2.0.dist-info/METADATA
openbb_cli-1.2.0.dist-info/WHEEL
openbb_cli-1.2.0.dist-info/entry_points.txt
openbb_cli-1.2.0.dist-info/RECORD
